pyarabicnlp/__init__.py
pyarabicnlp/stemmer/__init__.py
pyarabicnlp/stemmer/abstract_stemmer.py
pyarabicnlp/stemmer/isri_stemmer.py
pyarabicnlp/stemmer/snowball_stemmer.py
pyarabicnlp/transliteration/__init__.py
pyarabicnlp/transliteration/buckwalter.py
pyarabicnlp-0.0.1.dist-info/LICENCE
pyarabicnlp-0.0.1.dist-info/METADATA
pyarabicnlp-0.0.1.dist-info/WHEEL
pyarabicnlp-0.0.1.dist-info/top_level.txt
pyarabicnlp-0.0.1.dist-info/RECORD
